{
    "Play": "Play",
    "Pause": "Pause",
    "Mute": "Mute",
    "Unmute": "Unmute",
    "Settings": "Settings",
    "Load State": "Load State",
    "Save State": "Save State",
    "Screenshot": "Screenshot",
    "Full Screen": "Full Screen",
    "Exit Full Screen": "Exit Full Screen",
    "Volume": "Volume",
    "Controls": "Controls",
    "Save": "Save",
    "Load": "Load",
    "Reset": "Reset",
    "Cheats": "Cheats",
    "Gamepad": "Gamepad",
    "Keyboard": "Keyboard",
    "Touch": "Touch",
    "Loading": "Loading",
    "Start": "Start",
    "Network Error": "Network Error",
    "CRC": "CRC",
    "Download": "Download",
    "Extracting": "Extracting",
    "Done": "Done"
}
